hledger_tui/__init__.py
hledger_tui/__main__.py
hledger_tui/app.py
hledger_tui/config.py
hledger_tui/core/models.py
hledger_tui/core/parser.py
hledger_tui/core/period.py
hledger_tui/core/service.py
hledger_tui/ui/base/base_modal.py
hledger_tui/ui/base/base_tab.py
hledger_tui/ui/modals/account_overview.py
hledger_tui/ui/modals/tag_overview.py
hledger_tui/ui/modals/tag_pivot.py
hledger_tui/ui/modals/transaction_list.py
hledger_tui/ui/tabs/assets.py
hledger_tui/ui/tabs/balance.py
hledger_tui/ui/tabs/statistics.py
hledger_tui/ui/widgets/account_datatable.py
hledger_tui/ui/widgets/grid_footer.py
hledger_tui/ui/widgets/hledger_assets.py
hledger_tui/ui/widgets/hledger_balance.py
hledger_tui/ui/widgets/hledger_statistics.py
hledger_tui/ui/widgets/plots/bar_plot.py
hledger_tui/ui/widgets/plots/base_plot.py
hledger_tui/ui/widgets/plots/line_plot.py
hledger_tui-0.1.0.dist-info/licenses/LICENSE
hledger_tui-0.1.0.dist-info/WHEEL
hledger_tui-0.1.0.dist-info/entry_points.txt
hledger_tui-0.1.0.dist-info/METADATA
hledger_tui-0.1.0.dist-info/RECORD
