Metadata-Version: 2.4
Name: hledger-tui
Version: 0.1.0
Summary: A Textual TUI to view HLedger data.
Author: Luca Bello
Author-email: Luca Bello <lusgabello@gmail.com>
License-File: LICENSE
Requires-Dist: textual
Requires-Dist: textual-dev
Requires-Dist: textual-plotext
Requires-Dist: sh
Requires-Dist: typer
Requires-Dist: dataconfy
Requires-Python: >=3.10
Project-URL: Homepage, https://github.com/lucabello/hledger-tui
Project-URL: Repository, https://github.com/lucabello/hledger-tui
Project-URL: Issues, https://github.com/lucabello/hledger-tui/issues
